{
    "sceneName": "Scena26S",
    "background": "groem 17-01",
    "camera": {
        "startPoint": {
            "x": -1.3899999856948853,
            "y": -2.059999942779541,
            "z": -10.0
        },
        "size": 3.5,
        "actor": "",
        "min": {
            "x": 0.0,
            "y": 0.0
        },
        "max": {
            "x": 0.0,
            "y": 0.0
        }
    },
    "entities": [
        {
            "name": "Aquila",
            "type": 0,
            "renderLayer": 0,
            "flip": true,
            "idleState": 0,
            "start": {
                "x": 0.05999999865889549,
                "y": -4.090000152587891
            },
            "scale": {
                "x": 1.0,
                "y": 1.0
            },
            "stateLayer": ""
        },
        {
            "name": "Pinoside",
            "type": 0,
            "renderLayer": 0,
            "flip": false,
            "idleState": 0,
            "start": {
                "x": -3.8989999294281008,
                "y": -3.140000104904175
            },
            "scale": {
                "x": 0.6000000238418579,
                "y": 0.6000000238418579
            },
            "stateLayer": "GuardaAlto"
        }
    ],
    "waypoints": [
        {
            "name": "StartPino",
            "position": {
                "x": -3.8989999294281008,
                "y": -3.140000104904175
            },
            "scale": {
                "x": 0.6000000238418579,
                "y": 0.6000000238418579
            }
        },
        {
            "name": "StartAquila",
            "position": {
                "x": 0.05999999865889549,
                "y": -4.090000152587891
            },
            "scale": {
                "x": 1.0,
                "y": 1.0
            }
        },
        {
            "name": "EndAquila",
            "position": {
                "x": -7.230000019073486,
                "y": 4.019999980926514
            },
            "scale": {
                "x": 1.0,
                "y": 1.0
            }
        }
    ]
}
